biosimulators_masspy/__init__.py
biosimulators_masspy/__main__.py
biosimulators_masspy/_version.py
biosimulators_masspy/core.py
biosimulators_masspy/data_model.py
biosimulators_masspy-0.1.2.dist-info/LICENSE
biosimulators_masspy-0.1.2.dist-info/METADATA
biosimulators_masspy-0.1.2.dist-info/WHEEL
biosimulators_masspy-0.1.2.dist-info/entry_points.txt
biosimulators_masspy-0.1.2.dist-info/RECORD
