Metadata-Version: 2.1
Name: biosimulators-masspy
Version: 0.1.2
Summary: BioSimulators-compliant command-line interface to the MassPY simulation program <https://masspy.readthedocs.io/>.
Home-page: https://masspy.readthedocs.io/
License: MIT
Keywords: systems,biology,modeling,simulation
Author: Center for Reproducible Biomedical Modeling
Author-email: info@biosimulators.org
Requires-Python: >=3.9,<4.0
Classifier: Development Status :: 3 - Alpha
Classifier: Intended Audience :: Science/Research
Classifier: License :: OSI Approved :: MIT License
Classifier: Programming Language :: Python :: 3
Classifier: Programming Language :: Python :: 3.9
Classifier: Programming Language :: Python :: 3.10
Classifier: Programming Language :: Python :: 3.11
Classifier: Programming Language :: Python :: 3.12
Classifier: Topic :: Scientific/Engineering :: Bio-Informatics
Requires-Dist: biosimulators_utils[logging,sbml] (>=0.1.151,<0.2.0)
Requires-Dist: cobra (<=0.23.0)
Requires-Dist: docker (>=7.1.0,<8.0.0)
Requires-Dist: kisao (>=2.34,<3.0)
Requires-Dist: libroadrunner (>2.2.0)
Requires-Dist: lxml (>=4.5,<5.0)
Requires-Dist: masspy (>=0.1.7,<0.2.0)
Requires-Dist: numpy (<1.24.0)
Project-URL: Repository, https://github.com/biosimulators/Biosimulators_MassPy
